techx/__init__.py
techx/html_renderer.py
techx/intermediate.py
techx/main.py
techx/parser.py
techx/pdf_renderer.py
techx/tokenizer.py
techx-0.1.dist-info/LICENSE
techx-0.1.dist-info/METADATA
techx-0.1.dist-info/WHEEL
techx-0.1.dist-info/entry_points.txt
techx-0.1.dist-info/top_level.txt
techx-0.1.dist-info/RECORD
