Metadata-Version: 2.1
Name: techx
Version: 0.1
Summary: A typesetting system for quick and easy technical documentation.
Home-page: https://github.com/SidZRed/TEchX
Author: Siddharth Reddy
Author-email: siddharthrr@iisc.ac.in
Classifier: Programming Language :: Python :: 3
Classifier: License :: OSI Approved :: MIT License
Classifier: Operating System :: OS Independent
Requires-Python: >=3.6
License-File: LICENSE
Requires-Dist: reportlab
